README.md
setup.py
jinja2_ext_required/__init__.py
jinja2_required_variables_extension.egg-info/PKG-INFO
jinja2_required_variables_extension.egg-info/SOURCES.txt
jinja2_required_variables_extension.egg-info/dependency_links.txt
jinja2_required_variables_extension.egg-info/requires.txt
jinja2_required_variables_extension.egg-info/top_level.txt