Metadata-Version: 1.0
Name: jinja2-required-variables-extension
Version: 0.1.2
Summary: A custom Jinja tag `required`: ignore enclosed block of content if any of the variables is empty
Home-page: https://github.com/wewearglasses/jinja2-required-variables-extension
Author: Shang Liang
Author-email: shang@wewearglasses.com
License: MIT
Platform: UNKNOWN
